{
  "timestamp": "2025-09-18T18:20:07.947560",
  "last_check": "2025-09-18T18:20:07.947559",
  "pages": {
    "main_dashboard": {
      "status": "error",
      "error": "Cannot connect to host localhost:8080 ssl:default [Multiple exceptions: [Errno 111] Connect call failed ('::1', 8080, 0, 0), [Errno 111] Connect call failed ('127.0.0.1', 8080)]",
      "response_time": 0.0013704299926757812,
      "timestamp": "2025-09-18T18:20:07.944795"
    },
    "chat": {
      "status": "error",
      "error": "Cannot connect to host localhost:8080 ssl:default [Multiple exceptions: [Errno 111] Connect call failed ('::1', 8080, 0, 0), [Errno 111] Connect call failed ('127.0.0.1', 8080)]",
      "response_time": 0.0011382102966308594,
      "timestamp": "2025-09-18T18:20:07.946036"
    },
    "vision": {
      "status": "error",
      "error": "Cannot connect to host localhost:8080 ssl:default [Multiple exceptions: [Errno 111] Connect call failed ('::1', 8080, 0, 0), [Errno 111] Connect call failed ('127.0.0.1', 8080)]",
      "response_time": 0.0007033348083496094,
      "timestamp": "2025-09-18T18:20:07.946815"
    },
    "visual_report": {
      "status": "error",
      "error": "Cannot connect to host localhost:8080 ssl:default [Multiple exceptions: [Errno 111] Connect call failed ('::1', 8080, 0, 0), [Errno 111] Connect call failed ('127.0.0.1', 8080)]",
      "response_time": 0.0006334781646728516,
      "timestamp": "2025-09-18T18:20:07.947504"
    }
  },
  "summary": {
    "total_pages": 4,
    "working_pages": 0,
    "error_pages": 4,
    "success_rate": 0.0,
    "avg_response_time": 0
  }
}