{
  "timestamp": "2025-09-18T18:06:36.871945",
  "last_check": "2025-09-18T18:06:36.871944",
  "pages": {
    "main_dashboard": {
      "status": "error",
      "error": "Cannot connect to host localhost:8080 ssl:default [Multiple exceptions: [Errno 111] Connect call failed ('::1', 8080, 0, 0), [Errno 111] Connect call failed ('127.0.0.1', 8080)]",
      "response_time": 0.001062631607055664,
      "timestamp": "2025-09-18T18:06:36.869889"
    },
    "chat": {
      "status": "error",
      "error": "Cannot connect to host localhost:8080 ssl:default [Multiple exceptions: [Errno 111] Connect call failed ('::1', 8080, 0, 0), [Errno 111] Connect call failed ('127.0.0.1', 8080)]",
      "response_time": 0.0007987022399902344,
      "timestamp": "2025-09-18T18:06:36.870755"
    },
    "vision": {
      "status": "error",
      "error": "Cannot connect to host localhost:8080 ssl:default [Multiple exceptions: [Errno 111] Connect call failed ('::1', 8080, 0, 0), [Errno 111] Connect call failed ('127.0.0.1', 8080)]",
      "response_time": 0.0004937648773193359,
      "timestamp": "2025-09-18T18:06:36.871299"
    },
    "visual_report": {
      "status": "error",
      "error": "Cannot connect to host localhost:8080 ssl:default [Multiple exceptions: [Errno 111] Connect call failed ('::1', 8080, 0, 0), [Errno 111] Connect call failed ('127.0.0.1', 8080)]",
      "response_time": 0.0005438327789306641,
      "timestamp": "2025-09-18T18:06:36.871890"
    }
  },
  "summary": {
    "total_pages": 4,
    "working_pages": 0,
    "error_pages": 4,
    "success_rate": 0.0,
    "avg_response_time": 0
  }
}